radiate-0.0.10.dist-info/METADATA
radiate-0.0.10.dist-info/WHEEL
radiate/__init__.py
radiate/__version__.py
radiate/_typing.py
radiate/builder.py
radiate/codec/__init__.py
radiate/codec/any.py
radiate/codec/base.py
radiate/codec/bit.py
radiate/codec/char.py
radiate/codec/float.py
radiate/codec/graph.py
radiate/codec/int.py
radiate/codec/permutation.py
radiate/codec/tree.py
radiate/dependancies.py
radiate/engine.py
radiate/fitness/__init__.py
radiate/fitness/base.py
radiate/fitness/custom.py
radiate/fitness/novelty.py
radiate/fitness/regression.py
radiate/generation.py
radiate/genome/__init__.py
radiate/genome/chromosome.py
radiate/genome/ecosystem.py
radiate/genome/gene.py
radiate/genome/genotype.py
radiate/genome/phenotype.py
radiate/genome/population.py
radiate/genome/species.py
radiate/gp/__init__.py
radiate/gp/graph.py
radiate/gp/op.py
radiate/gp/tree.py
radiate/handlers.py
radiate/inputs/__init__.py
radiate/inputs/alterer.py
radiate/inputs/component.py
radiate/inputs/descriptor.py
radiate/inputs/distance.py
radiate/inputs/executor.py
radiate/inputs/input.py
radiate/inputs/limit.py
radiate/inputs/selector.py
radiate/metrics.py
radiate/option.py
radiate/py.typed
radiate/radiate.cpython-313t-i386-linux-gnu.so
radiate/random.py
radiate/wrapper.py
radiate-0.0.10.dist-info/RECORD
