Metadata-Version: 2.4
Name: radiate
Version: 0.0.10
Classifier: Programming Language :: Rust
Classifier: Programming Language :: Python :: Implementation :: CPython
Classifier: Programming Language :: Python :: Implementation :: PyPy
Classifier: Programming Language :: Python :: 3.12
Classifier: Programming Language :: Python :: 3.13
Classifier: Programming Language :: Python :: 3.14
Classifier: License :: OSI Approved :: MIT License
Classifier: Operating System :: OS Independent
Classifier: Development Status :: 4 - Beta
Classifier: Intended Audience :: Science/Research
Classifier: Topic :: Scientific/Engineering :: Physics
Summary: A fast and flexible evolution engine for implementing artificial evolution and genetic programming techniques.
Home-Page: https://pkalivas.github.io/radiate/
Author-email: Peter Kalivas <peterkalivas@gmail.com>
Requires-Python: >=3.12
